bulir/VERSION
bulir/__init__.py
bulir/bulir.py
bulir-2020.4.12.0.dist-info/LICENSE
bulir-2020.4.12.0.dist-info/METADATA
bulir-2020.4.12.0.dist-info/WHEEL
bulir-2020.4.12.0.dist-info/entry_points.txt
bulir-2020.4.12.0.dist-info/top_level.txt
bulir-2020.4.12.0.dist-info/RECORD
