Metadata-Version: 2.1
Name: bulir
Version: 2020.4.12.0
Summary: Brazilian UF Lawsuit IDs in no time!
Home-page: https://github.com/ayharano/bulir
Author: Alexandre Harano
Author-email: email@ayharano.dev
License: MIT
Keywords: brazilian uf lawsuit
Platform: any
Classifier: Development Status :: 4 - Beta
Classifier: Environment :: Console
Classifier: Framework :: AsyncIO
Classifier: Intended Audience :: Legal Industry
Classifier: License :: OSI Approved :: MIT License
Classifier: Natural Language :: English
Classifier: Operating System :: OS Independent
Classifier: Programming Language :: Python
Classifier: Programming Language :: Python :: 3
Classifier: Programming Language :: Python :: 3 :: Only
Classifier: Programming Language :: Python :: 3.7
Classifier: Topic :: Utilities
Requires-Python: >=3.7
Requires-Dist: cfscrape
Requires-Dist: lxml
Requires-Dist: yarl
Requires-Dist: anyio
Requires-Dist: asyncclick
